rstspreadsheet.py
setup.py
rstspreadsheet.egg-info/PKG-INFO
rstspreadsheet.egg-info/SOURCES.txt
rstspreadsheet.egg-info/dependency_links.txt
rstspreadsheet.egg-info/top_level.txt