Metadata-Version: 1.0
Name: rstspreadsheet
Version: 0.1.2
Summary: Add the `spreadsheet` directive to reStructuredText for Docutils and Sphinx
Home-page: UNKNOWN
Author: Takafumi Arakaki
Author-email: aka.tkf@gmail.com
License: MIT License
Platform: UNKNOWN
Classifier: Development Status :: 3 - Alpha
Classifier: Intended Audience :: Science/Research
Classifier: Intended Audience :: Developers
Classifier: License :: OSI Approved :: MIT License
Classifier: Programming Language :: Python
Classifier: Topic :: Documentation
Classifier: Topic :: Utilities
